rtc_cafe_signaller/__init__.py
rtc_cafe_signaller/wrappers/__init__.py
rtc_cafe_signaller/wrappers/flask_socketio_wrapper.py
rtc_cafe_signaller_python-0.2.0.dist-info/METADATA
rtc_cafe_signaller_python-0.2.0.dist-info/WHEEL
rtc_cafe_signaller_python-0.2.0.dist-info/top_level.txt
rtc_cafe_signaller_python-0.2.0.dist-info/RECORD
