Metadata-Version: 2.1
Name: rtc-cafe-signaller-python
Version: 0.2.0
Summary: UNKNOWN
Home-page: https://gitlab.com/rtc-cafe/rtc-cafe-signaller-python
License: UNKNOWN
Platform: UNKNOWN
